<worksheet xmlns="http://schemas.openxmlformats.org/spreadsheetml/2006/main"><sheetPr><outlinePr summaryBelow="1" summaryRight="1" /><pageSetUpPr /></sheetPr><dimension ref="A1:G10" /><sheetViews><sheetView workbookViewId="0"><selection activeCell="A1" sqref="A1" /></sheetView></sheetViews><sheetFormatPr baseColWidth="8" defaultRowHeight="15" /><sheetData><row r="1"><c r="A1" t="inlineStr"><is><t>id</t></is></c><c r="B1" t="inlineStr"><is><t>affix_key</t></is></c><c r="C1" t="inlineStr"><is><t>modifier_type</t></is></c><c r="D1" t="inlineStr"><is><t>min_per_level</t></is></c><c r="E1" t="inlineStr"><is><t>max_per_level</t></is></c><c r="F1" t="inlineStr"><is><t>slot_mask</t></is></c></row><row r="2"><c r="A2" t="inlineStr"><is><t>int</t></is></c><c r="B2" t="inlineStr"><is><t>string</t></is></c><c r="C2" t="inlineStr"><is><t>int</t></is></c><c r="D2" t="inlineStr"><is><t>float</t></is></c><c r="E2" t="inlineStr"><is><t>float</t></is></c><c r="F2" t="inlineStr"><is><t>int</t></is></c></row><row r="3"><c r="F3" t="inlineStr"><is><t>comma</t></is></c></row><row r="4"></row><row r="5"><c r="A5" t="inlineStr"><is><t>词条 ID</t></is></c><c r="B5" t="inlineStr"><is><t>词条逻辑 ID</t></is></c><c r="C5" t="inlineStr"><is><t>ModifierType 枚举值 1=固定 2=百分比</t></is></c><c r="D5" t="inlineStr"><is><t>每级最小系数</t></is></c><c r="E5" t="inlineStr"><is><t>每级最大系数</t></is></c><c r="F5" t="inlineStr"><is><t>可出现的装备槽 slot_type 列表</t></is></c></row><row r="6"><c r="A6" t="n"><v>1</v></c><c r="B6" t="inlineStr"><is><t>affix.vitality</t></is></c><c r="C6" t="n"><v>100</v></c><c r="D6" t="n"><v>1</v></c><c r="E6" t="n"><v>2</v></c><c r="F6" t="n"><v>5</v></c><c r="G6" t="inlineStr"><is><t>2,3,4,5</t></is></c></row><row r="7"><c r="A7" t="n"><v>2</v></c><c r="B7" t="inlineStr"><is><t>affix.might</t></is></c><c r="C7" t="n"><v>102</v></c><c r="D7" t="n"><v>2</v></c><c r="E7" t="n"><v>0.01</v></c><c r="F7" t="n"><v>0.03</v></c><c r="G7" t="inlineStr"><is><t>1,5</t></is></c></row><row r="8"><c r="A8" t="n"><v>3</v></c><c r="B8" t="inlineStr"><is><t>affix.swiftness</t></is></c><c r="C8" t="n"><v>104</v></c><c r="D8" t="n"><v>2</v></c><c r="E8" t="n"><v>0.005</v></c><c r="F8" t="n"><v>0.015</v></c><c r="G8" t="inlineStr"><is><t>4,5</t></is></c></row><row r="9"><c r="A9" t="n"><v>4</v></c><c r="B9" t="inlineStr"><is><t>affix.precision</t></is></c><c r="C9" t="n"><v>110</v></c><c r="D9" t="n"><v>2</v></c><c r="E9" t="n"><v>0.01</v></c><c r="F9" t="n"><v>0.04</v></c><c r="G9" t="inlineStr"><is><t>1,2,5</t></is></c></row><row r="10"><c r="A10" t="n"><v>5</v></c><c r="B10" t="inlineStr"><is><t>affix.fortitude</t></is></c><c r="C10" t="n"><v>111</v></c><c r="D10" t="n"><v>1</v></c><c r="E10" t="n"><v>1</v></c><c r="F10" t="n"><v>3</v></c><c r="G10" t="inlineStr"><is><t>2,3,4</t></is></c></row></sheetData><pageMargins left="0.75" right="0.75" top="1" bottom="1" header="0.5" footer="0.5" /></worksheet>